setup.py
playground_decision_tree/DecisionTreeClassifier.py
playground_decision_tree/NodeClass.py
playground_decision_tree/__init__.py
playground_decision_tree.egg-info/PKG-INFO
playground_decision_tree.egg-info/SOURCES.txt
playground_decision_tree.egg-info/dependency_links.txt
playground_decision_tree.egg-info/not-zip-safe
playground_decision_tree.egg-info/top_level.txt