Metadata-Version: 1.0
Name: playground-decision-tree
Version: 0.1
Summary: a playground decision tree
Home-page: UNKNOWN
Author: UNKNOWN
Author-email: UNKNOWN
License: UNKNOWN
Platform: UNKNOWN
